verysimpletest/__init__.py
verysimpletest/add.py
verysimpletest/subtract.py
verysimpletest/extra/__init__.py
verysimpletest/extra/divide.py
verysimpletest/extra/multipy.py
verysimpletest-0.0.2.dist-info/LICENSE
verysimpletest-0.0.2.dist-info/METADATA
verysimpletest-0.0.2.dist-info/WHEEL
verysimpletest-0.0.2.dist-info/top_level.txt
verysimpletest-0.0.2.dist-info/RECORD
